resume_classification/__init__.py
resume_classification/config.py
resume_classification/utils.py
resume_classification/model/classes.npy
resume_classification/model/count_vect.pkl
resume_classification/model/latest_model.pkl
resume_classification/prediction/__init__.py
resume_classification/prediction/predict.py
resume_classification/training/__init__.py
resume_classification/training/train.py
resume_classification-1.0.dist-info/LICENSE
resume_classification-1.0.dist-info/METADATA
resume_classification-1.0.dist-info/WHEEL
resume_classification-1.0.dist-info/top_level.txt
resume_classification-1.0.dist-info/RECORD
