Metadata-Version: 2.1
Name: resume-classification
Version: 1.0
Summary: It a simple package for training and classification of resumes.
Home-page: https://github.com/shreyas2306/ResumeParser
Author: Shreyas Nanaware/Krushna Kumar Nalange
License: MIT
Platform: UNKNOWN
Classifier: License :: OSI Approved :: MIT License
Classifier: Programming Language :: Python :: 3
Classifier: Programming Language :: Python :: 3.7
Requires-Dist: numpy (==1.17.3)
Requires-Dist: pandas (==0.25.1)
Requires-Dist: tika (==1.24)
Requires-Dist: nltk (==3.4.5)
Requires-Dist: setuptools (==41.4.0)
Requires-Dist: Wheel (==0.33.6)
